[
    {
        "id": "f6f2187d.f17ca8",
        "type": "tab",
        "label": "Flow 1",
        "disabled": false,
        "info": ""
    },
    {
        "id": "70620482a316f58d",
        "type": "mqtt-broker",
        "name": "sae23",
        "broker": "mqtt.iut-blagnac.fr",
        "port": "1883",
        "clientid": "",
        "autoConnect": true,
        "usetls": false,
        "protocolVersion": "4",
        "keepalive": "60",
        "cleansession": true,
        "birthTopic": "",
        "birthQos": "0",
        "birthPayload": "",
        "birthMsg": {},
        "closeTopic": "",
        "closeQos": "0",
        "closePayload": "",
        "closeMsg": {},
        "willTopic": "",
        "willQos": "0",
        "willPayload": "",
        "willMsg": {},
        "userProps": "",
        "sessionExpiry": ""
    },
    {
        "id": "286e6aca8e75cf17",
        "type": "ui_tab",
        "name": "E208",
        "icon": "dashboard",
        "disabled": false,
        "hidden": false
    },
    {
        "id": "42f8a117ca2b4ccd",
        "type": "ui_base",
        "theme": {
            "name": "theme-light",
            "lightTheme": {
                "default": "#0094CE",
                "baseColor": "#0094CE",
                "baseFont": "-apple-system,BlinkMacSystemFont,Segoe UI,Roboto,Oxygen-Sans,Ubuntu,Cantarell,Helvetica Neue,sans-serif",
                "edited": false
            },
            "darkTheme": {
                "default": "#097479",
                "baseColor": "#097479",
                "baseFont": "-apple-system,BlinkMacSystemFont,Segoe UI,Roboto,Oxygen-Sans,Ubuntu,Cantarell,Helvetica Neue,sans-serif",
                "edited": false
            },
            "customTheme": {
                "name": "Untitled Theme 1",
                "default": "#4B7930",
                "baseColor": "#4B7930",
                "baseFont": "-apple-system,BlinkMacSystemFont,Segoe UI,Roboto,Oxygen-Sans,Ubuntu,Cantarell,Helvetica Neue,sans-serif"
            },
            "themeState": {
                "base-color": {
                    "default": "#0094CE",
                    "value": "#0094CE",
                    "edited": false
                },
                "page-titlebar-backgroundColor": {
                    "value": "#0094CE",
                    "edited": false
                },
                "page-backgroundColor": {
                    "value": "#fafafa",
                    "edited": false
                },
                "page-sidebar-backgroundColor": {
                    "value": "#ffffff",
                    "edited": false
                },
                "group-textColor": {
                    "value": "#1bbfff",
                    "edited": false
                },
                "group-borderColor": {
                    "value": "#ffffff",
                    "edited": false
                },
                "group-backgroundColor": {
                    "value": "#ffffff",
                    "edited": false
                },
                "widget-textColor": {
                    "value": "#111111",
                    "edited": false
                },
                "widget-backgroundColor": {
                    "value": "#0094ce",
                    "edited": false
                },
                "widget-borderColor": {
                    "value": "#ffffff",
                    "edited": false
                },
                "base-font": {
                    "value": "-apple-system,BlinkMacSystemFont,Segoe UI,Roboto,Oxygen-Sans,Ubuntu,Cantarell,Helvetica Neue,sans-serif"
                }
            },
            "angularTheme": {
                "primary": "indigo",
                "accents": "blue",
                "warn": "red",
                "background": "grey",
                "palette": "light"
            }
        },
        "site": {
            "name": "Node-RED Dashboard",
            "hideToolbar": "false",
            "allowSwipe": "false",
            "lockMenu": "false",
            "allowTempTheme": "true",
            "dateFormat": "DD/MM/YYYY",
            "sizes": {
                "sx": 48,
                "sy": 48,
                "gx": 6,
                "gy": 6,
                "cx": 6,
                "cy": 6,
                "px": 0,
                "py": 0
            }
        }
    },
    {
        "id": "06124f2ec4219865",
        "type": "ui_group",
        "name": "E208",
        "tab": "286e6aca8e75cf17",
        "order": 1,
        "disp": true,
        "width": "6",
        "collapse": false,
        "className": ""
    },
    {
        "id": "dfcd9a280f208cec",
        "type": "ui_tab",
        "name": "B106",
        "icon": "dashboard",
        "disabled": false,
        "hidden": false
    },
    {
        "id": "b24f5d5ea04ca358",
        "type": "ui_group",
        "name": "B106",
        "tab": "dfcd9a280f208cec",
        "order": 1,
        "disp": true,
        "width": "6",
        "collapse": false,
        "className": ""
    },
    {
        "id": "440ecaa03d6c5246",
        "type": "influxdb",
        "hostname": "192.168.105.229",
        "port": "8086",
        "protocol": "http",
        "database": "SAE23",
        "name": "SAE23",
        "usetls": false,
        "tls": "",
        "influxdbVersion": "1.x",
        "url": "http://localhost:8086",
        "rejectUnauthorized": true
    },
    {
        "id": "cff3a3e08a335fc7",
        "type": "mqtt in",
        "z": "f6f2187d.f17ca8",
        "name": "mqtt sae23",
        "topic": "Student/by-room/#",
        "qos": "2",
        "datatype": "auto-detect",
        "broker": "70620482a316f58d",
        "nl": false,
        "rap": true,
        "rh": 0,
        "inputs": 0,
        "x": 80,
        "y": 360,
        "wires": [
            [
                "849cedf1318d5c13"
            ]
        ]
    },
    {
        "id": "1c4bec90bb294c54",
        "type": "change",
        "z": "f6f2187d.f17ca8",
        "name": "",
        "rules": [
            {
                "t": "set",
                "p": "payload",
                "pt": "msg",
                "to": "$number(payload[0].temperature)",
                "tot": "jsonata"
            }
        ],
        "action": "",
        "property": "",
        "from": "",
        "to": "",
        "reg": false,
        "x": 380,
        "y": 120,
        "wires": [
            [
                "0ab5432cfd92da3f",
                "9a08939e2453cf7f"
            ]
        ]
    },
    {
        "id": "3e6461c88a89653e",
        "type": "change",
        "z": "f6f2187d.f17ca8",
        "name": "",
        "rules": [
            {
                "t": "set",
                "p": "payload",
                "pt": "msg",
                "to": "$number(payload[0].co2)",
                "tot": "jsonata"
            }
        ],
        "action": "",
        "property": "",
        "from": "",
        "to": "",
        "reg": false,
        "x": 380,
        "y": 180,
        "wires": [
            [
                "a79b48dcda81f618",
                "3c7f8fd9c89bfbdc"
            ]
        ]
    },
    {
        "id": "610bf2d5a3f4e2b3",
        "type": "change",
        "z": "f6f2187d.f17ca8",
        "name": "",
        "rules": [
            {
                "t": "set",
                "p": "payload",
                "pt": "msg",
                "to": "$number(payload[0].humidity)",
                "tot": "jsonata"
            }
        ],
        "action": "",
        "property": "",
        "from": "",
        "to": "",
        "reg": false,
        "x": 380,
        "y": 240,
        "wires": [
            [
                "a14a1ff55a380347",
                "faeb611d59336775"
            ]
        ]
    },
    {
        "id": "e30e57760499f3f1",
        "type": "change",
        "z": "f6f2187d.f17ca8",
        "name": "",
        "rules": [
            {
                "t": "set",
                "p": "payload",
                "pt": "msg",
                "to": "$number(payload[0].humidity)",
                "tot": "jsonata"
            }
        ],
        "action": "",
        "property": "",
        "from": "",
        "to": "",
        "reg": false,
        "x": 380,
        "y": 540,
        "wires": [
            [
                "1fec79910910b220",
                "e005bb6fa8af778c"
            ]
        ]
    },
    {
        "id": "e5a98128d9a37019",
        "type": "change",
        "z": "f6f2187d.f17ca8",
        "name": "",
        "rules": [
            {
                "t": "set",
                "p": "payload",
                "pt": "msg",
                "to": "$number(payload[0].co2)",
                "tot": "jsonata"
            }
        ],
        "action": "",
        "property": "",
        "from": "",
        "to": "",
        "reg": false,
        "x": 380,
        "y": 480,
        "wires": [
            [
                "307a65bbe468f090",
                "fbce3d01e33e0d7d"
            ]
        ]
    },
    {
        "id": "d4f9b23e239aec33",
        "type": "change",
        "z": "f6f2187d.f17ca8",
        "name": "",
        "rules": [
            {
                "t": "set",
                "p": "payload",
                "pt": "msg",
                "to": "$number(payload[0].temperature)",
                "tot": "jsonata"
            }
        ],
        "action": "",
        "property": "",
        "from": "",
        "to": "",
        "reg": false,
        "x": 380,
        "y": 420,
        "wires": [
            [
                "4eeb33380a2d3b22",
                "1336e89e68dbc823"
            ]
        ]
    },
    {
        "id": "0ab5432cfd92da3f",
        "type": "ui_gauge",
        "z": "f6f2187d.f17ca8",
        "name": "Temperature",
        "group": "06124f2ec4219865",
        "order": 0,
        "width": 0,
        "height": 0,
        "gtype": "gage",
        "title": "temperature",
        "label": "°C",
        "format": "{{value}}",
        "min": 0,
        "max": "40",
        "colors": [
            "#00b500",
            "#e6e600",
            "#ca3838"
        ],
        "seg1": "15",
        "seg2": "25",
        "diff": false,
        "className": "",
        "x": 610,
        "y": 120,
        "wires": []
    },
    {
        "id": "a79b48dcda81f618",
        "type": "ui_gauge",
        "z": "f6f2187d.f17ca8",
        "name": "co2",
        "group": "06124f2ec4219865",
        "order": 1,
        "width": 0,
        "height": 0,
        "gtype": "gage",
        "title": "co2",
        "label": "ppm",
        "format": "{{value}}",
        "min": 0,
        "max": "1600",
        "colors": [
            "#00b500",
            "#e6e600",
            "#ca3838"
        ],
        "seg1": "540",
        "seg2": "775",
        "diff": false,
        "className": "",
        "x": 590,
        "y": 180,
        "wires": []
    },
    {
        "id": "a14a1ff55a380347",
        "type": "ui_gauge",
        "z": "f6f2187d.f17ca8",
        "name": "humidié",
        "group": "06124f2ec4219865",
        "order": 2,
        "width": 0,
        "height": 0,
        "gtype": "gage",
        "title": "Humidité",
        "label": "%",
        "format": "{{value}}",
        "min": 0,
        "max": "100",
        "colors": [
            "#00b500",
            "#e6e600",
            "#ca3838"
        ],
        "seg1": "33",
        "seg2": "66",
        "diff": false,
        "className": "",
        "x": 600,
        "y": 240,
        "wires": []
    },
    {
        "id": "1fec79910910b220",
        "type": "ui_gauge",
        "z": "f6f2187d.f17ca8",
        "name": "humidié",
        "group": "b24f5d5ea04ca358",
        "order": 2,
        "width": 0,
        "height": 0,
        "gtype": "gage",
        "title": "Humidité",
        "label": "%",
        "format": "{{value}}",
        "min": 0,
        "max": "100",
        "colors": [
            "#00b500",
            "#e6e600",
            "#ca3838"
        ],
        "seg1": "33",
        "seg2": "66",
        "diff": false,
        "className": "",
        "x": 600,
        "y": 540,
        "wires": []
    },
    {
        "id": "307a65bbe468f090",
        "type": "ui_gauge",
        "z": "f6f2187d.f17ca8",
        "name": "co2",
        "group": "b24f5d5ea04ca358",
        "order": 1,
        "width": 0,
        "height": 0,
        "gtype": "gage",
        "title": "co2",
        "label": "ppm",
        "format": "{{value}}",
        "min": 0,
        "max": "1600",
        "colors": [
            "#00b500",
            "#e6e600",
            "#ca3838"
        ],
        "seg1": "540",
        "seg2": "775",
        "diff": false,
        "className": "",
        "x": 590,
        "y": 480,
        "wires": []
    },
    {
        "id": "4eeb33380a2d3b22",
        "type": "ui_gauge",
        "z": "f6f2187d.f17ca8",
        "name": "Temperature",
        "group": "b24f5d5ea04ca358",
        "order": 0,
        "width": 0,
        "height": 0,
        "gtype": "gage",
        "title": "temperature",
        "label": "°C",
        "format": "{{value}}",
        "min": 0,
        "max": "40",
        "colors": [
            "#00b500",
            "#e6e600",
            "#ca3838"
        ],
        "seg1": "15",
        "seg2": "25",
        "diff": false,
        "className": "",
        "x": 610,
        "y": 420,
        "wires": []
    },
    {
        "id": "9a08939e2453cf7f",
        "type": "influxdb out",
        "z": "f6f2187d.f17ca8",
        "influxdb": "440ecaa03d6c5246",
        "name": "temp",
        "measurement": "temperature,building=E,room=E208",
        "precision": "",
        "retentionPolicy": "",
        "database": "database",
        "precisionV18FluxV20": "ms",
        "retentionPolicyV18Flux": "",
        "org": "organisation",
        "bucket": "bucket",
        "x": 590,
        "y": 80,
        "wires": []
    },
    {
        "id": "849cedf1318d5c13",
        "type": "switch",
        "z": "f6f2187d.f17ca8",
        "name": "",
        "property": "topic",
        "propertyType": "msg",
        "rules": [
            {
                "t": "eq",
                "v": "Student/by-room/E208/data",
                "vt": "str"
            },
            {
                "t": "eq",
                "v": "Student/by-room/B106/data",
                "vt": "str"
            }
        ],
        "checkall": "true",
        "repair": false,
        "outputs": 2,
        "x": 230,
        "y": 360,
        "wires": [
            [
                "1c4bec90bb294c54",
                "3e6461c88a89653e",
                "610bf2d5a3f4e2b3"
            ],
            [
                "d4f9b23e239aec33",
                "e5a98128d9a37019",
                "e30e57760499f3f1"
            ]
        ]
    },
    {
        "id": "1336e89e68dbc823",
        "type": "influxdb out",
        "z": "f6f2187d.f17ca8",
        "influxdb": "440ecaa03d6c5246",
        "name": "temp",
        "measurement": "temperature,building=B,room=B106",
        "precision": "",
        "retentionPolicy": "",
        "database": "database",
        "precisionV18FluxV20": "ms",
        "retentionPolicyV18Flux": "",
        "org": "organisation",
        "bucket": "bucket",
        "x": 590,
        "y": 380,
        "wires": []
    },
    {
        "id": "fbce3d01e33e0d7d",
        "type": "influxdb out",
        "z": "f6f2187d.f17ca8",
        "influxdb": "440ecaa03d6c5246",
        "name": "CO2",
        "measurement": "co2,building=B,room=B106",
        "precision": "",
        "retentionPolicy": "",
        "database": "database",
        "precisionV18FluxV20": "ms",
        "retentionPolicyV18Flux": "",
        "org": "organisation",
        "bucket": "bucket",
        "x": 730,
        "y": 480,
        "wires": []
    },
    {
        "id": "e005bb6fa8af778c",
        "type": "influxdb out",
        "z": "f6f2187d.f17ca8",
        "influxdb": "440ecaa03d6c5246",
        "name": "humidity",
        "measurement": "humidity,building=B,room=B106",
        "precision": "",
        "retentionPolicy": "",
        "database": "database",
        "precisionV18FluxV20": "ms",
        "retentionPolicyV18Flux": "",
        "org": "organisation",
        "bucket": "bucket",
        "x": 600,
        "y": 580,
        "wires": []
    },
    {
        "id": "faeb611d59336775",
        "type": "influxdb out",
        "z": "f6f2187d.f17ca8",
        "influxdb": "440ecaa03d6c5246",
        "name": "humidity",
        "measurement": "humidity,building=E,room=E208",
        "precision": "",
        "retentionPolicy": "",
        "database": "database",
        "precisionV18FluxV20": "ms",
        "retentionPolicyV18Flux": "",
        "org": "organisation",
        "bucket": "bucket",
        "x": 600,
        "y": 280,
        "wires": []
    },
    {
        "id": "3c7f8fd9c89bfbdc",
        "type": "influxdb out",
        "z": "f6f2187d.f17ca8",
        "influxdb": "440ecaa03d6c5246",
        "name": "CO2",
        "measurement": "co2,building=E,room=E208",
        "precision": "",
        "retentionPolicy": "",
        "database": "database",
        "precisionV18FluxV20": "ms",
        "retentionPolicyV18Flux": "",
        "org": "organisation",
        "bucket": "bucket",
        "x": 730,
        "y": 180,
        "wires": []
    }
]